tl2cgen.libs/libgomp-a34b3233.so.1.0.0
tl2cgen-1.0.0.dist-info/METADATA
tl2cgen-1.0.0.dist-info/WHEEL
tl2cgen-1.0.0.dist-info/RECORD
tl2cgen/shortcuts.py
tl2cgen/util.py
tl2cgen/exception.py
tl2cgen/core.py
tl2cgen/handle_class.py
tl2cgen/create_shared.py
tl2cgen/__init__.py
tl2cgen/generate_makefile.py
tl2cgen/data.py
tl2cgen/predictor.py
tl2cgen/dtypes.py
tl2cgen/libloader.py
tl2cgen/py.typed
tl2cgen/VERSION
tl2cgen/contrib/util.py
tl2cgen/contrib/gcc.py
tl2cgen/contrib/create_shared.py
tl2cgen/contrib/__init__.py
tl2cgen/contrib/msvc.py
tl2cgen/lib/libtl2cgen.so
